<suite name="All sites">

 <!--   <listeners>
        <listener class-name="org.testng.reporters.EmailableReporter2" />
    </listeners>
-->

    <listeners>
        <listener class-name="org.uncommons.reportng.HTMLReporter"/>
        <listener class-name="org.uncommons.reportng.JUnitXMLReporter"/>
    </listeners>


    <test name="career">
        <classes>
            <class name = "TestNGDemo.DemoReal.JobSites"/>
            <class name = "TestNGDemo.DemoReal.TutorialsSites"/>
        </classes>
    </test>


    <test name="social">
        <classes>
            <class name="TestNGDemo.DemoReal.SocialSites"/>
        </classes>
    </test>

</suite>